fulldict.py
fulldict-0.1.0.dist-info/LICENSE
fulldict-0.1.0.dist-info/WHEEL
fulldict-0.1.0.dist-info/METADATA
fulldict-0.1.0.dist-info/RECORD
