Metadata-Version: 2.1
Name: fulldict
Version: 0.1.0
Summary: Dictionaries with multiple functionalities.
Home-page: https://github.com/revensky/fulldict
License: MIT
Author: Eduardo Rezende
Author-email: eduardorbr7@gmail.com
Requires-Python: >=3.8,<4.0
Classifier: Development Status :: 4 - Beta
Classifier: Intended Audience :: Developers
Classifier: License :: OSI Approved :: MIT License
Classifier: Operating System :: OS Independent
Classifier: Programming Language :: Python :: 3
Classifier: Programming Language :: Python :: 3.8
Classifier: Programming Language :: Python :: 3.9
Classifier: Typing :: Typed
Project-URL: Repository, https://github.com/revensky/fulldict.git
